pytestdiv.py
pytestdiv-0.3.1.dist-info/METADATA
pytestdiv-0.3.1.dist-info/WHEEL
pytestdiv-0.3.1.dist-info/entry_points.txt
pytestdiv-0.3.1.dist-info/top_level.txt
pytestdiv-0.3.1.dist-info/RECORD
